discrust-0.1.6.dist-info/METADATA
discrust-0.1.6.dist-info/WHEEL
discrust-0.1.6.dist-info/license_files/LICENSE
discrust/__init__.py
discrust/discrust.cpython-39-darwin.so
discrust-0.1.6.dist-info/RECORD
