Metadata-Version: 2.1
Name: discrust
Version: 0.1.6
Requires-Dist: numpy>=1.21
Requires-Dist: pandas>=1.3
License-File: LICENSE
Summary: Supervised discretization with Rust
Keywords: rust,discretize,scorecard,numpy,machine learning
Author: James Inlow
Maintainer: James Inlow
